conexions/__init__.py
conexions/dto_proxy.py
conexions/excepcions.py
conexions/proxy.py
conexions-1.3.dist-info/LICENSE
conexions-1.3.dist-info/METADATA
conexions-1.3.dist-info/WHEEL
conexions-1.3.dist-info/top_level.txt
conexions-1.3.dist-info/RECORD
