Metadata-Version: 2.1
Name: conexions
Version: 1.3
Summary: Módulo para distintos unificado de conexións web
Home-page: https://www.github.com/Ran-n/conexions
Author: Ran#
Author-email: ran-n@tutanota.com
License: GPLv3
Project-URL: Bug Tracker, https://www.github.com/Ran-n/conexions/issues
Platform: UNKNOWN
Classifier: Development Status :: 3 - Alpha
Classifier: Environment :: Console
Classifier: Intended Audience :: Developers
Classifier: License :: OSI Approved :: GNU General Public License v3 (GPLv3)
Classifier: Operating System :: OS Independent
Classifier: Programming Language :: Python :: 3.8
Classifier: Topic :: Software Development :: Libraries
Classifier: Natural Language :: Galician
Classifier: Natural Language :: Portuguese
Classifier: Natural Language :: English
Classifier: Natural Language :: Spanish
Requires-Python: >=3.8.5
License-File: LICENSE
Requires-Dist: beautifulsoup4 (==4.10.0)
Requires-Dist: fake-useragent (==0.1.11)
Requires-Dist: halo (==0.0.31)
Requires-Dist: requests (==2.26.0)
